final_project/base/__init__.py
final_project/base/base.py
final_project/builder/__init__.py
final_project/builder/builder.py
final_project/loader/__init__.py
final_project/loader/loader.py
final_project/models/__init__.py
final_project/models/feed_forward.py
final_project/models/models.py
final_project/plots/__init__.py
final_project/plots/plots.py
final_project/roc/__init__.py
final_project/roc/roc.py
cs6141_final_project-0.1.3.dist-info/METADATA
cs6141_final_project-0.1.3.dist-info/WHEEL
cs6141_final_project-0.1.3.dist-info/RECORD
