Metadata-Version: 2.1
Name: cs6141-final-project
Version: 0.1.3
Summary: To infinity, and beyond!
Author: Daniel Blum
Author-email: blum.da@northeastern.edu
Requires-Python: >=3.9,<4.0
Classifier: Programming Language :: Python :: 3
Classifier: Programming Language :: Python :: 3.9
Classifier: Programming Language :: Python :: 3.10
Classifier: Programming Language :: Python :: 3.11
Requires-Dist: black[jupyter] (>=23.3.0,<24.0.0)
Requires-Dist: jupyterlab (>=3.6.3,<4.0.0)
Requires-Dist: matplotlib (>=3.7.1,<4.0.0)
Requires-Dist: numpy (==1.23.5)
Requires-Dist: pandas (>=1.5.3,<2.0.0)
Requires-Dist: pyyaml (>=6.0,<7.0)
Requires-Dist: scikit-learn (>=1.2.2,<2.0.0)
Requires-Dist: seaborn (>=0.12.2,<0.13.0)
Requires-Dist: tabulate (>=0.9.0,<0.10.0)
Requires-Dist: torch (>=2.0.0,<3.0.0)
Requires-Dist: tqdm (>=4.65.0,<5.0.0)
